<Automation screen="LM201000">
    <Fields ScreenID="LM201000">
        <Field IsActive="True" DisplayName="Customer" FieldName="CUSTOMERID" ObjectName="LUMCUSTOMIZATIONS.DAC.LUMSHIPMENTPLAN" />
        <Field IsActive="True" DisplayName="Customer Location" FieldName="CUSTOMERLOCATIONID" ObjectName="LUMCUSTOMIZATIONS.DAC.LUMSHIPMENTPLAN" />
    </Fields>
    <Actions ScreenID="LM201000">
        <Action IsActive="True" ActionName="CopyPaste" ActionType="G" WindowMode="S" HideCondition="True">
            <StateActionFields />
            <StateActionParams />
        </Action>
        <Action IsActive="True" ActionName="Delete" ActionType="G" WindowMode="S">
            <StateActionFields />
            <StateActionParams />
        </Action>
        <Action IsActive="True" ActionName="First" ActionType="G" WindowMode="S" HideCondition="True">
            <StateActionFields />
            <StateActionParams />
        </Action>
        <Action IsActive="True" ActionName="Insert" ActionType="G" WindowMode="S" HideCondition="True">
            <StateActionFields />
            <StateActionParams />
        </Action>
        <Action IsActive="True" ActionName="Last" ActionType="G" WindowMode="S" HideCondition="True">
            <StateActionFields />
            <StateActionParams />
        </Action>
        <Action IsActive="True" ActionName="Next" ActionType="G" WindowMode="S" HideCondition="True">
            <StateActionFields />
            <StateActionParams />
        </Action>
        <Action IsActive="True" ActionName="Previous" ActionType="G" WindowMode="S" HideCondition="True">
            <StateActionFields />
            <StateActionParams />
        </Action>
    </Actions>
</Automation>